./.env
./PKG-INFO
./README.md
./captcha.png
./main.py
./pyproject.toml
./requirements.txt
./stdio_main.py
./.idea/.gitignore
./.idea/mcp-server.iml
./.idea/misc.xml
./.idea/modules.xml
./.idea/vcs.xml
./.idea/workspace.xml
./config/settings.py
./core/server.py
./core/utils.py
./tools/base.py
./tools/flowInfo/__init__.py
./tools/flowInfo/service.py
./tools/flowInfo/tool.py
./tools/time/__init__.py
./tools/time/tool.py
tcl_auto_deploy_demo-0.1.9.dist-info/METADATA
tcl_auto_deploy_demo-0.1.9.dist-info/WHEEL
tcl_auto_deploy_demo-0.1.9.dist-info/entry_points.txt
tcl_auto_deploy_demo-0.1.9.dist-info/RECORD
